mcp_server_bigquery/__init__.py
mcp_server_bigquery/server.py
gfg_mcp_server_bigquery-0.3.2.dist-info/METADATA
gfg_mcp_server_bigquery-0.3.2.dist-info/WHEEL
gfg_mcp_server_bigquery-0.3.2.dist-info/entry_points.txt
gfg_mcp_server_bigquery-0.3.2.dist-info/licenses/LICENSE
gfg_mcp_server_bigquery-0.3.2.dist-info/RECORD
