Metadata-Version: 2.4
Name: gfg-mcp-server-bigquery
Version: 0.3.2
Summary: A Model Context Protocol server that provides access to BigQuery. This server enables LLMs to inspect database schemas and execute queries.
Author: Lucas Hild
License-File: LICENSE
Requires-Python: >=3.13
Requires-Dist: google-cloud-bigquery>=3.27.0
Requires-Dist: mcp>=1.0.0
